sbatchpy/__init__.py
sbatchpy-1.0.0.dist-info/LICENCE
sbatchpy-1.0.0.dist-info/METADATA
sbatchpy-1.0.0.dist-info/WHEEL
sbatchpy-1.0.0.dist-info/top_level.txt
sbatchpy-1.0.0.dist-info/RECORD
