Metadata-Version: 2.1
Name: sbatchpy
Version: 1.0.0
Summary: Sbatchpy is a python package allowing easy sbatch job script creation and submissions on hpc clusters, directly from python.
Home-page: https://github.com/killiansheriff/sbatchpy
Author: Killian Sheriff
Author-email: ksheriff@mit.edu
License: MIT
Keywords: sbatch,slurm,python,hpc
License-File: LICENCE
